scrapy_huo_utilities/__init__.py
scrapy_huo_utilities/MIDDLEWARES/__init__.py
scrapy_huo_utilities/MIDDLEWARES/Downloader_Middleware_Utils.py
scrapy_huo_utilities/MIDDLEWARES/Spider_Middleware_Utils.py
scrapy_huo_utilities/MIDDLEWARES/test.py
scrapy_huo_utilities/PROCESSORS/__init__.py
scrapy_huo_utilities/PROCESSORS/html_clean.py
scrapy_huo_utilities-0.0.4.dist-info/LICENSE
scrapy_huo_utilities-0.0.4.dist-info/METADATA
scrapy_huo_utilities-0.0.4.dist-info/WHEEL
scrapy_huo_utilities-0.0.4.dist-info/RECORD
