Metadata-Version: 2.1
Name: scrapy_huo_utilities
Version: 0.0.4
Summary: scrapy_huo_utilities是自用的一些scrapy工具代码合集。
Home-page: https://gitee.com/ranvane/scrapy_huo_utilities
License: MIT
Author: ranvane
Author-email: ranvane@gmail.com
Requires-Python: >=3.5,<4.0
Classifier: License :: OSI Approved :: MIT License
Classifier: Programming Language :: Python :: 3
Classifier: Programming Language :: Python :: 3.5
Classifier: Programming Language :: Python :: 3.6
Classifier: Programming Language :: Python :: 3.7
Classifier: Programming Language :: Python :: 3.8
Classifier: Programming Language :: Python :: 3.9
Classifier: Programming Language :: Python :: 3.10
Classifier: Programming Language :: Python :: 3.11
Classifier: Programming Language :: Python :: 3.12
Requires-Dist: fake-agent (>=0.1.4,<0.2.0)
Requires-Dist: loguru (>=0.7.2,<0.8.0)
Requires-Dist: lxml (>=4.8.0,<5.0.0)
Requires-Dist: plyvel_wheels (>=1.3.0,<2.0.0)
Requires-Dist: scrapy (>=2.0.0,<3.0.0)
Project-URL: Repository, https://gitee.com/ranvane/scrapy_huo_utilities
